{"version":1,"resource":"file:///Users/yyx/Library/Mobile%20Documents/com~apple~CloudDocs/RyukyuUniversity/code/unity/quest_open_compus/Assets/Scripts/TouchMoving.cs","entries":[{"id":"BnhV.cs","timestamp":1720794559742},{"id":"QVNy.cs","timestamp":1720794582099},{"id":"CHNQ.cs","timestamp":1720794620531},{"id":"8LgL.cs","timestamp":1720794748541},{"id":"Pj12.cs","timestamp":1720794759180},{"id":"uBbq.cs","timestamp":1720795097124},{"id":"SC2K.cs","timestamp":1720795124828},{"id":"jmur.cs","timestamp":1720796212448},{"id":"9C7g.cs","timestamp":1720800213909},{"id":"4RZP.cs","timestamp":1720800227683},{"id":"7geX.cs","timestamp":1720800571392},{"id":"c1w6.cs","timestamp":1720800710258},{"id":"cwaB.cs","timestamp":1720800739186},{"id":"T63Q.cs","timestamp":1720800917298},{"id":"Cxyh.cs","timestamp":1720800946111},{"id":"kSrU.cs","timestamp":1720801158355},{"id":"aqZY.cs","timestamp":1720801358733},{"id":"W5Bm.cs","timestamp":1720801378319},{"id":"VFKm.cs","timestamp":1720801389664},{"id":"UDME.cs","timestamp":1720801401056},{"id":"XR3P.cs","timestamp":1720801866650},{"id":"rdwo.cs","timestamp":1720802238052},{"id":"zBYI.cs","timestamp":1720802275417},{"id":"pDep.cs","timestamp":1720802431687},{"id":"wtCg.cs","timestamp":1720802443527},{"id":"RXta.cs","timestamp":1720802629943},{"id":"V0AH.cs","timestamp":1720802885825},{"id":"DJ7Z.cs","timestamp":1720802901158},{"id":"bZAW.cs","timestamp":1720802917687},{"id":"sPzI.cs","timestamp":1720803709002},{"id":"mjqU.cs","timestamp":1720803742074},{"id":"FeUT.cs","timestamp":1720803794074},{"id":"HpJH.cs","timestamp":1720803816472},{"id":"I9Xr.cs","timestamp":1720803830621},{"id":"DFzE.cs","timestamp":1720803860802},{"id":"xDWs.cs","timestamp":1720804016256},{"id":"FCSv.cs","timestamp":1720804228253},{"id":"lmnt.cs","timestamp":1720804252749},{"id":"B242.cs","timestamp":1720804391915},{"id":"glfp.cs","timestamp":1720804405885},{"id":"Ab7A.cs","timestamp":1720804602123},{"id":"0rQV.cs","timestamp":1720804618189},{"id":"21t3.cs","timestamp":1720804635133},{"id":"MGDY.cs","timestamp":1720809196286},{"id":"O9s9.cs","timestamp":1720809301161},{"id":"pJG3.cs","timestamp":1720809760841},{"id":"Rxxe.cs","timestamp":1720809795139},{"id":"KSPG.cs","timestamp":1720809814589},{"id":"Fgpa.cs","timestamp":1720809829872},{"id":"INtp.cs","timestamp":1720810620920}]}